patrole_tempest_plugin/__init__.py
patrole_tempest_plugin/config.py
patrole_tempest_plugin/plugin.py
patrole_tempest_plugin/policy_authority.py
patrole_tempest_plugin/rbac_authority.py
patrole_tempest_plugin/rbac_exceptions.py
patrole_tempest_plugin/rbac_rule_validation.py
patrole_tempest_plugin/rbac_utils.py
patrole_tempest_plugin/requirements_authority.py
patrole_tempest_plugin/version.py
patrole_tempest_plugin/hacking/__init__.py
patrole_tempest_plugin/hacking/checks.py
patrole_tempest_plugin/tests/__init__.py
patrole_tempest_plugin/tests/api/README.rst
patrole_tempest_plugin/tests/api/__init__.py
patrole_tempest_plugin/tests/api/compute/__init__.py
patrole_tempest_plugin/tests/api/compute/rbac_base.py
patrole_tempest_plugin/tests/api/compute/test_agents_rbac.py
patrole_tempest_plugin/tests/api/compute/test_aggregates_rbac.py
patrole_tempest_plugin/tests/api/compute/test_availability_zone_rbac.py
patrole_tempest_plugin/tests/api/compute/test_flavor_access_rbac.py
patrole_tempest_plugin/tests/api/compute/test_flavor_extra_specs_rbac.py
patrole_tempest_plugin/tests/api/compute/test_flavor_manage_rbac.py
patrole_tempest_plugin/tests/api/compute/test_flavor_rxtx_rbac.py
patrole_tempest_plugin/tests/api/compute/test_floating_ip_pools_rbac.py
patrole_tempest_plugin/tests/api/compute/test_floating_ips_rbac.py
patrole_tempest_plugin/tests/api/compute/test_hosts_rbac.py
patrole_tempest_plugin/tests/api/compute/test_hypervisor_rbac.py
patrole_tempest_plugin/tests/api/compute/test_images_rbac.py
patrole_tempest_plugin/tests/api/compute/test_instance_usages_audit_log_rbac.py
patrole_tempest_plugin/tests/api/compute/test_keypairs_rbac.py
patrole_tempest_plugin/tests/api/compute/test_limits_rbac.py
patrole_tempest_plugin/tests/api/compute/test_migrations_rbac.py
patrole_tempest_plugin/tests/api/compute/test_quota_class_sets_rbac.py
patrole_tempest_plugin/tests/api/compute/test_quota_sets_rbac.py
patrole_tempest_plugin/tests/api/compute/test_security_groups_rbac.py
patrole-0.16.0.dist-info/AUTHORS
patrole-0.16.0.dist-info/LICENSE
patrole-0.16.0.dist-info/METADATA
patrole-0.16.0.dist-info/WHEEL
patrole-0.16.0.dist-info/entry_points.txt
patrole-0.16.0.dist-info/pbr.json
patrole-0.16.0.dist-info/top_level.txt
patrole-0.16.0.dist-info/RECORD
