Metadata-Version: 2.1
Name: patrole
Version: 0.16.0
Summary: Patrole is a tool for verifying that Role-Based Access Control is being enforced across OpenStack deployments.
Home-page: https://docs.openstack.org/patrole/latest/
Author: OpenStack
Author-email: openstack-discuss@lists.openstack.org
License: UNKNOWN
Platform: UNKNOWN
Classifier: Environment :: OpenStack
Classifier: Intended Audience :: Information Technology
Classifier: Intended Audience :: System Administrators
Classifier: License :: OSI Approved :: Apache Software License
Classifier: Operating System :: POSIX :: Linux
Classifier: Programming Language :: Python
Classifier: Programming Language :: Python :: Implementation :: CPython
Classifier: Programming Language :: Python :: 3 :: Only
Classifier: Programming Language :: Python :: 3
Classifier: Programming Language :: Python :: 3.6
Classifier: Programming Language :: Python :: 3.7
Classifier: Programming Language :: Python :: 3.8
Requires-Python: >=3.6
Requires-Dist: oslo.config (>=5.2.0)
Requires-Dist: oslo.log (>=3.36.0)
Requires-Dist: oslo.policy (>=1.30.0)
Requires-Dist: pbr (!=2.1.0,>=2.0.0)
Requires-Dist: stevedore (>=1.20.0)
Requires-Dist: tempest (>=30.0.0)
